{
  "ComponentIndexes": {
    "NevigationBar": 6,
    "NevigationBar_1": 6
  },
  "ControlUniqueGuids": {},
  "ControlUniqueIds": {
    "App": 1,
    "BS_W_DataCard1": 69,
    "BS_W_DataCard2": 183,
    "BS_W_DataCard3": 137,
    "BS_W_DataCard4": 222,
    "btn_contine": 265,
    "btn_contine_1": 386,
    "btn_Explore": 300,
    "btn_galTabSelecteds": 22,
    "btn_mob_exploreNow": 342,
    "btn_Trans": 264,
    "btn_Trans_1": 384,
    "Button1": 165,
    "Button2": 198,
    "Button2_1": 250,
    "Button3": 246,
    "Circle3": 9,
    "Closing_Tank_Stock_BBLS_DataCard1": 153,
    "ComboBox1": 385,
    "con_kpi2": 277,
    "con_kpi3": 278,
    "con_kpi4": 279,
    "con_kpi5": 280,
    "con_main1": 267,
    "con_mainHeader": 268,
    "con_mainNev": 5,
    "con_nevigation": 281,
    "con_notification": 271,
    "con_userImage": 273,
    "cont_buttonHolder": 298,
    "cont_ContentFormScreen": 18,
    "cont_FlyingSVGArrow": 301,
    "cont_FooterContent": 304,
    "cont_FooterContent_1": 305,
    "cont_FooterContent_2": 311,
    "cont_FooterContent_3": 317,
    "cont_FooterContent_4": 323,
    "cont_FooterContent_5": 346,
    "cont_FooterContent_6": 352,
    "cont_FooterContent_7": 359,
    "cont_FooterContent_8": 365,
    "cont_HeaderRegionalForm_1": 27,
    "cont_HeaderRegionalForm_2": 13,
    "cont_kpi1": 276,
    "cont_leftContent": 19,
    "cont_leftSideOfMain": 285,
    "cont_logIn": 258,
    "cont_logIn_1": 374,
    "cont_logoHeader": 286,
    "cont_Main_persona": 256,
    "cont_Main_persona_1": 371,
    "cont_mainBackground": 284,
    "cont_MainFormScreen": 12,
    "cont_mainKpi": 275,
    "cont_messageContent": 293,
    "cont_mob_backgroundImage": 335,
    "cont_mob_footerAboveContent": 345,
    "cont_mob_footerAboveContent_1": 358,
    "cont_mob_FooterContents": 344,
    "cont_mob_LeftSideContent": 337,
    "cont_mob_logoImage": 332,
    "cont_mob_main(MainLanding)": 331,
    "cont_personaSize": 263,
    "cont_personaSize_1": 379,
    "cont_rightContent": 25,
    "cont_rightSideOfMain": 329,
    "cont_Sales_Jaipur": 201,
    "cont_Sales_Jaisalmer": 205,
    "cont_Sales_Jodhpur": 202,
    "cont_Sales_Kota": 203,
    "cont_Sales_Udaipur": 204,
    "cont_subMainPersona": 257,
    "cont_subMainPersona_1": 373,
    "cont_subPersona": 380,
    "cont_WelcomeMessage": 289,
    "Container10": 8,
    "Container11": 242,
    "Container13": 247,
    "Container15": 245,
    "Container6": 239,
    "Container7": 240,
    "Container8": 254,
    "Container9": 241,
    "Cumulative_Till_Date_DataCard1": 80,
    "DataCardKey1": 36,
    "DataCardKey10": 175,
    "DataCardKey11": 180,
    "DataCardKey12": 185,
    "DataCardKey13": 190,
    "DataCardKey14": 195,
    "DataCardKey15": 77,
    "DataCardKey16": 82,
    "DataCardKey17": 210,
    "DataCardKey18": 88,
    "DataCardKey19": 93,
    "DataCardKey2": 41,
    "DataCardKey20": 98,
    "DataCardKey21": 215,
    "DataCardKey22": 104,
    "DataCardKey23": 109,
    "DataCardKey24": 114,
    "DataCardKey25": 119,
    "DataCardKey26": 124,
    "DataCardKey27": 129,
    "DataCardKey28": 134,
    "DataCardKey29": 139,
    "DataCardKey3": 46,
    "DataCardKey30": 220,
    "DataCardKey31": 145,
    "DataCardKey32": 150,
    "DataCardKey33": 155,
    "DataCardKey34": 160,
    "DataCardKey35": 225,
    "DataCardKey36": 230,
    "DataCardKey37": 235,
    "DataCardKey4": 51,
    "DataCardKey5": 56,
    "DataCardKey6": 61,
    "DataCardKey7": 66,
    "DataCardKey8": 71,
    "DataCardKey9": 170,
    "DataCardValue1": 37,
    "DataCardValue10": 176,
    "DataCardValue11": 181,
    "DataCardValue12": 186,
    "DataCardValue13": 191,
    "DataCardValue14": 196,
    "DataCardValue15": 78,
    "DataCardValue16": 83,
    "DataCardValue17": 208,
    "DataCardValue18": 89,
    "DataCardValue19": 94,
    "DataCardValue2": 42,
    "DataCardValue20": 99,
    "DataCardValue21": 213,
    "DataCardValue22": 105,
    "DataCardValue23": 110,
    "DataCardValue24": 115,
    "DataCardValue25": 120,
    "DataCardValue26": 125,
    "DataCardValue27": 130,
    "DataCardValue28": 135,
    "DataCardValue29": 140,
    "DataCardValue3": 47,
    "DataCardValue30": 218,
    "DataCardValue31": 146,
    "DataCardValue32": 151,
    "DataCardValue33": 156,
    "DataCardValue34": 161,
    "DataCardValue35": 223,
    "DataCardValue36": 228,
    "DataCardValue37": 233,
    "DataCardValue4": 52,
    "DataCardValue5": 57,
    "DataCardValue6": 62,
    "DataCardValue7": 67,
    "DataCardValue8": 72,
    "DataCardValue9": 171,
    "Density_15C_DataCard1": 193,
    "Density_15C_DataCard2": 232,
    "Duration_hours_DataCard1": 64,
    "Duration_hours_DataCard2": 132,
    "ErrorMessage1": 38,
    "ErrorMessage10": 177,
    "ErrorMessage11": 182,
    "ErrorMessage12": 187,
    "ErrorMessage13": 192,
    "ErrorMessage14": 197,
    "ErrorMessage15": 79,
    "ErrorMessage16": 84,
    "ErrorMessage17": 211,
    "ErrorMessage18": 90,
    "ErrorMessage19": 95,
    "ErrorMessage2": 43,
    "ErrorMessage20": 100,
    "ErrorMessage21": 216,
    "ErrorMessage22": 106,
    "ErrorMessage23": 111,
    "ErrorMessage24": 116,
    "ErrorMessage25": 121,
    "ErrorMessage26": 126,
    "ErrorMessage27": 131,
    "ErrorMessage28": 136,
    "ErrorMessage29": 141,
    "ErrorMessage3": 48,
    "ErrorMessage30": 221,
    "ErrorMessage31": 147,
    "ErrorMessage32": 152,
    "ErrorMessage33": 157,
    "ErrorMessage34": 162,
    "ErrorMessage35": 226,
    "ErrorMessage36": 231,
    "ErrorMessage37": 236,
    "ErrorMessage4": 53,
    "ErrorMessage5": 58,
    "ErrorMessage6": 63,
    "ErrorMessage7": 68,
    "ErrorMessage8": 73,
    "ErrorMessage9": 172,
    "Form Screen": 11,
    "Form_Sales_Jaisalmer": 206,
    "Form_Screen": 199,
    "Form1": 33,
    "Form2": 167,
    "Form3": 74,
    "Form4": 85,
    "Form5": 101,
    "Form7": 142,
    "gal_mainNev": 6,
    "gal_personaSize": 261,
    "gal_personaSize_1": 377,
    "gal_tempTabItems": 20,
    "Gallery1": 163,
    "Gallery1_1": 248,
    "galleryTemplate1": 164,
    "galleryTemplate1_1": 249,
    "galleryTemplate2": 21,
    "galleryTemplate4": 7,
    "galleryTemplate6": 262,
    "galleryTemplate6_1": 378,
    "Gross_Sales_DataCard1": 173,
    "Gross_Sales_DataCard2": 212,
    "Gross_Volume_pumped_DataCard1": 39,
    "Gross_Volume_pumped_DataCard2": 107,
    "Home Page Screen": 266,
    "Host": 3,
    "Image1": 372,
    "Image3_1": 251,
    "Image4": 255,
    "Image5": 10,
    "img_collaboration": 307,
    "img_collaboration_1": 348,
    "img_FlyingArrow": 303,
    "img_logoOIlMine": 333,
    "img_mob_flyingArrow": 343,
    "img_mob_oilMineBackground": 336,
    "img_notification": 272,
    "img_oilLogoHeader_1": 28,
    "img_oilLogoHeader_2": 14,
    "img_OIlLogoImg": 287,
    "img_oilMineImageRightSideMain": 330,
    "img_persona": 382,
    "img_RegionalForm_UserImage_1": 30,
    "img_RegionalForm_UserImage_2": 17,
    "img_relatability": 319,
    "img_relatability_1": 361,
    "img_safety_1": 313,
    "img_safety_2": 354,
    "img_solutionFooter": 325,
    "img_solutionFooter_1": 367,
    "img_userImage": 274,
    "Label3": 243,
    "Label5": 244,
    "lbl_collabContent": 310,
    "lbl_collabContent_1": 351,
    "lbl_Collaboration": 309,
    "lbl_Collaboration_1": 350,
    "lbl_flex": 270,
    "lbl_footSolution": 327,
    "lbl_footSolution_1": 369,
    "lbl_gap_1": 290,
    "lbl_gap_2": 292,
    "lbl_gap_3": 297,
    "lbl_gap1": 381,
    "lbl_LoggedInUserName_1": 29,
    "lbl_LoggedInUserName_2": 16,
    "lbl_LogIn": 259,
    "lbl_LogIn_1": 375,
    "lbl_LogoMessageOilMine": 288,
    "lbl_messageContent": 295,
    "lbl_MessageHeading": 291,
    "lbl_mob_gap_1": 341,
    "lbl_mob_Heading": 339,
    "lbl_mob_headingContent": 340,
    "lbl_mob_logoMessage": 334,
    "lbl_mob_topGap_1": 338,
    "lbl_RegionalForm_LogoHeader_1": 31,
    "lbl_RegionalForm_LogoHeader_2": 15,
    "lbl_relatability": 321,
    "lbl_relatability_1": 363,
    "lbl_relatibilityContent": 322,
    "lbl_relatibilityContent_1": 364,
    "lbl_safety_1": 315,
    "lbl_safety_2": 356,
    "lbl_safetyContent_1": 316,
    "lbl_safetyContent_2": 357,
    "lbl_sideGap_1": 294,
    "lbl_sideGap_2": 299,
    "lbl_sideGap_3": 302,
    "lbl_sideGap_content": 296,
    "Lbl_Size": 260,
    "Lbl_Size_1": 376,
    "lbl_solutionContent": 328,
    "lbl_solutionContent_1": 370,
    "lbl_TabItemstemp": 23,
    "lbl_topfooterGap": 306,
    "lbl_topfooterGap_1": 308,
    "lbl_topfooterGap_10": 353,
    "lbl_topfooterGap_11": 355,
    "lbl_topfooterGap_12": 360,
    "lbl_topfooterGap_13": 362,
    "lbl_topfooterGap_14": 366,
    "lbl_topfooterGap_15": 368,
    "lbl_topfooterGap_2": 312,
    "lbl_topfooterGap_3": 314,
    "lbl_topfooterGap_4": 318,
    "lbl_topfooterGap_5": 320,
    "lbl_topfooterGap_6": 324,
    "lbl_topfooterGap_7": 326,
    "lbl_topfooterGap_8": 347,
    "lbl_topfooterGap_9": 349,
    "lbl_typeOfPersona": 383,
    "lbl_welcome": 269,
    "Main Container": 200,
    "Main Landing Screen (Dynamic)": 283,
    "Net_Sales_DataCard1": 178,
    "Net_Sales_DataCard2": 217,
    "NevigationBar": 4,
    "NevigationBar_1": 282,
    "Nomination_Met_DataCard1": 96,
    "RAAG_Oil_RDG_DataCard1": 54,
    "RAAG_Oil_RDG_DataCard2": 122,
    "Receipt_Tankage_only_BBLS_DataCard1": 148,
    "rect_tabItemGal": 24,
    "Sales_Value_DataCard1": 91,
    "Screen1": 26,
    "Screen2": 237,
    "ScreenContainer1": 238,
    "ScreenContainer2": 32,
    "Shortfall_Excess_NetMonth_DataCard1": 188,
    "Shortfall_Excess_NetMonth_DataCard2": 227,
    "StarVisible1": 35,
    "StarVisible10": 174,
    "StarVisible11": 179,
    "StarVisible12": 184,
    "StarVisible13": 189,
    "StarVisible14": 194,
    "StarVisible15": 76,
    "StarVisible16": 81,
    "StarVisible17": 209,
    "StarVisible18": 87,
    "StarVisible19": 92,
    "StarVisible2": 40,
    "StarVisible20": 97,
    "StarVisible21": 214,
    "StarVisible22": 103,
    "StarVisible23": 108,
    "StarVisible24": 113,
    "StarVisible25": 118,
    "StarVisible26": 123,
    "StarVisible27": 128,
    "StarVisible28": 133,
    "StarVisible29": 138,
    "StarVisible3": 45,
    "StarVisible30": 219,
    "StarVisible31": 144,
    "StarVisible32": 149,
    "StarVisible33": 154,
    "StarVisible34": 159,
    "StarVisible35": 224,
    "StarVisible36": 229,
    "StarVisible37": 234,
    "StarVisible4": 50,
    "StarVisible5": 55,
    "StarVisible6": 60,
    "StarVisible7": 65,
    "StarVisible8": 70,
    "StarVisible9": 169,
    "Subtitle1_1": 253,
    "Tank _DataCard1": 59,
    "Tank _DataCard2": 127,
    "Title_DataCard1": 34,
    "Title_DataCard2": 168,
    "Title_DataCard3": 75,
    "Title_DataCard4": 86,
    "Title_DataCard5": 102,
    "Title_DataCard6": 143,
    "Title_DataCard7": 207,
    "Title1_1": 252,
    "Title4": 166,
    "Total_Gross_Pumped_DataCard1": 49,
    "Total_Gross_Pumped_DataCard2": 117,
    "Total_Nomination_DataCard1": 44,
    "Total_Nomination_DataCard2": 112,
    "Water_Drain_Quantity_BBLS_DataCard1": 158
  },
  "FunctionParamsInvariantScripts": {},
  "FunctionParamsInvariantScriptsOnInstances": {},
  "HeaderLastSavedDateTimeUTC": "01/04/2024 13:05:05",
  "IsLegacyComponentAllowGlobalScopeCase": false,
  "LocalConnectionIDReferences": {
    "ad35ed50-698e-48be-9427-a782a1a80ec5": "\"/providers/microsoft.powerapps/apis/shared_sharepointonline/connections/832938808e0b419c8dc90fe74f425501\"",
    "c5b2dfc5-6ce6-40d7-bfda-6011ac1e7b4a": "\"/providers/microsoft.powerapps/apis/shared_sharepointonline/connections/832938808e0b419c8dc90fe74f425501\""
  },
  "LocalDatabaseReferencesAsEmpty": false,
  "LocalResourceFileNames": {
    "1649": "0001.jpg",
    "64f5c287aa639b5b91ad3b0f_Rectangle (2)": "0002.svg",
    "7f951bda68241a57aa84929a95f120f9f082a9a0-1440x1054": "0003.svg",
    "9d2ea1b508c12a7d974e238d426589ad-removebg-preview": "0004.png",
    "adminImage": "0005.png",
    "blue-gradient-background": "0006.jpg",
    "field-with-oil-pump-jacks-surrounded-by-greenery-sunlight": "0007.jpg",
    "Hawa-Mahal-Jaipur": "0008.jpg",
    "imageedit_1_7296434249": "0010.jpg",
    "image-removebg-preview": "0009.png",
    "JAISALMER": "0011.jpg",
    "Jodhpur": "0012.jpg",
    "Kota": "0013.jpg",
    "miningBottomImage": "0014.jpg",
    "OIl Mining logo": "0015.jpg",
    "oil_mineLOGO": "0022.jpg",
    "oilBottomImg": "0016.jpg",
    "OilFooter": "0017.jpg",
    "oilFooter_3": "0019.jpg",
    "oilFooter_4": "0020.jpg",
    "oilFooterImage2": "0018.jpg",
    "oilMiningImageRoleBased": "0021.jpg",
    "pexels-codioful-(formerly-gradienta)-7130555": "0023.jpg",
    "pexels-gradienta-7130560": "0024.jpg",
    "supervisorImage": "0025.png",
    "t85j6-alj36": "0026.svg",
    "Udaipur": "0027.jpg"
  },
  "LocalResourceRootPaths": {
    "1649": "https://docserverpwaprodcin.blob.core.windows.net/285a469e-3ec3-4693-bc7e-310e07275a85-1/resource/Assets0Images00001.jpg?skoid=58690ece-ec83-4ce2-9ce8-883d4d6a54ee&sktid=975f013f-7f24-47e8-a7d3-abc4752bf346&skt=2024-01-04T12%3A28%3A59Z&ske=2024-01-05T12%3A43%3A59Z&sks=b&skv=2022-11-02&sv=2022-11-02&spr=https&se=2024-01-05T12%3A43%3A59Z&sr=b&sp=r&sig=AF55dBlPtnahCgP5ef%2Beoc1ysULy6H4MLKXpxanCr5M%3D",
    "64f5c287aa639b5b91ad3b0f_Rectangle (2)": "https://docserverpwaprodcin.blob.core.windows.net/285a469e-3ec3-4693-bc7e-310e07275a85-1/resource/Assets0Images00002.svg?skoid=58690ece-ec83-4ce2-9ce8-883d4d6a54ee&sktid=975f013f-7f24-47e8-a7d3-abc4752bf346&skt=2024-01-04T12%3A28%3A59Z&ske=2024-01-05T12%3A43%3A59Z&sks=b&skv=2022-11-02&sv=2022-11-02&spr=https&se=2024-01-05T12%3A43%3A59Z&sr=b&sp=r&sig=RQIOTEqGrXgb7yMUJphPm%2FtmyYuFBxeZBT6%2BUthRNN8%3D",
    "7f951bda68241a57aa84929a95f120f9f082a9a0-1440x1054": "https://docserverpwaprodcin.blob.core.windows.net/285a469e-3ec3-4693-bc7e-310e07275a85-1/resource/Assets0Images00003.svg?skoid=58690ece-ec83-4ce2-9ce8-883d4d6a54ee&sktid=975f013f-7f24-47e8-a7d3-abc4752bf346&skt=2024-01-04T12%3A28%3A59Z&ske=2024-01-05T12%3A43%3A59Z&sks=b&skv=2022-11-02&sv=2022-11-02&spr=https&se=2024-01-05T12%3A43%3A59Z&sr=b&sp=r&sig=bh5RAoWKvqYvipizPgpGhAObeppEOujgGit515DvpZ8%3D",
    "9d2ea1b508c12a7d974e238d426589ad-removebg-preview": "https://docserverpwaprodcin.blob.core.windows.net/285a469e-3ec3-4693-bc7e-310e07275a85-1/resource/Assets0Images00004.png?skoid=58690ece-ec83-4ce2-9ce8-883d4d6a54ee&sktid=975f013f-7f24-47e8-a7d3-abc4752bf346&skt=2024-01-04T12%3A28%3A59Z&ske=2024-01-05T12%3A43%3A59Z&sks=b&skv=2022-11-02&sv=2022-11-02&spr=https&se=2024-01-05T12%3A43%3A59Z&sr=b&sp=r&sig=qnMyqqJCm1embqFfKJl6GcuJyKSo51aHyakxqH%2F6NgY%3D",
    "adminImage": "https://docserverpwaprodcin.blob.core.windows.net/285a469e-3ec3-4693-bc7e-310e07275a85-1/resource/Assets0Images00005.png?skoid=58690ece-ec83-4ce2-9ce8-883d4d6a54ee&sktid=975f013f-7f24-47e8-a7d3-abc4752bf346&skt=2024-01-04T12%3A28%3A59Z&ske=2024-01-05T12%3A43%3A59Z&sks=b&skv=2022-11-02&sv=2022-11-02&spr=https&se=2024-01-05T12%3A43%3A59Z&sr=b&sp=r&sig=Gka3DGZxfTejetDCDc8xSsg4TmK%2FcU2nTp57Jfvi7xA%3D",
    "blue-gradient-background": "https://docserverpwaprodcin.blob.core.windows.net/285a469e-3ec3-4693-bc7e-310e07275a85-1/resource/Assets0Images00006.jpg?skoid=58690ece-ec83-4ce2-9ce8-883d4d6a54ee&sktid=975f013f-7f24-47e8-a7d3-abc4752bf346&skt=2024-01-04T12%3A28%3A59Z&ske=2024-01-05T12%3A43%3A59Z&sks=b&skv=2022-11-02&sv=2022-11-02&spr=https&se=2024-01-05T12%3A43%3A59Z&sr=b&sp=r&sig=F0ovhY7zjRWpyBZ6Pcl71kkVWqcW%2FEKFjcBgZn1RTJA%3D",
    "field-with-oil-pump-jacks-surrounded-by-greenery-sunlight": "https://docserverpwaprodcin.blob.core.windows.net/285a469e-3ec3-4693-bc7e-310e07275a85-1/resource/Assets0Images00007.jpg?skoid=58690ece-ec83-4ce2-9ce8-883d4d6a54ee&sktid=975f013f-7f24-47e8-a7d3-abc4752bf346&skt=2024-01-04T12%3A28%3A59Z&ske=2024-01-05T12%3A43%3A59Z&sks=b&skv=2022-11-02&sv=2022-11-02&spr=https&se=2024-01-05T12%3A43%3A59Z&sr=b&sp=r&sig=Tkn6l0SuZb5J3owIQJ6scdAIONU%2FzMIx%2Fj5FKaY5lww%3D",
    "Hawa-Mahal-Jaipur": "https://docserverpwaprodcin.blob.core.windows.net/285a469e-3ec3-4693-bc7e-310e07275a85-1/resource/Assets0Images00008.jpg?skoid=58690ece-ec83-4ce2-9ce8-883d4d6a54ee&sktid=975f013f-7f24-47e8-a7d3-abc4752bf346&skt=2024-01-04T12%3A28%3A59Z&ske=2024-01-05T12%3A43%3A59Z&sks=b&skv=2022-11-02&sv=2022-11-02&spr=https&se=2024-01-05T12%3A43%3A59Z&sr=b&sp=r&sig=FHzwd4M4l6mMUu4FAaC%2FYCqd%2BKSSF%2FRsprOkzXvuLxQ%3D",
    "imageedit_1_7296434249": "https://docserverpwaprodcin.blob.core.windows.net/285a469e-3ec3-4693-bc7e-310e07275a85-1/resource/Assets0Images00010.jpg?skoid=58690ece-ec83-4ce2-9ce8-883d4d6a54ee&sktid=975f013f-7f24-47e8-a7d3-abc4752bf346&skt=2024-01-04T12%3A28%3A59Z&ske=2024-01-05T12%3A43%3A59Z&sks=b&skv=2022-11-02&sv=2022-11-02&spr=https&se=2024-01-05T12%3A43%3A59Z&sr=b&sp=r&sig=pTGRojbZmctd3EZvxegG2QWIsygbyXdgPrGErd%2F76ZA%3D",
    "image-removebg-preview": "https://docserverpwaprodcin.blob.core.windows.net/285a469e-3ec3-4693-bc7e-310e07275a85-1/resource/Assets0Images00009.png?skoid=58690ece-ec83-4ce2-9ce8-883d4d6a54ee&sktid=975f013f-7f24-47e8-a7d3-abc4752bf346&skt=2024-01-04T12%3A28%3A59Z&ske=2024-01-05T12%3A43%3A59Z&sks=b&skv=2022-11-02&sv=2022-11-02&spr=https&se=2024-01-05T12%3A43%3A59Z&sr=b&sp=r&sig=YKncTetcdYenMGXB9HNH6%2Bocdj%2BIjxuZN6RHLF8EbuE%3D",
    "JAISALMER": "https://docserverpwaprodcin.blob.core.windows.net/285a469e-3ec3-4693-bc7e-310e07275a85-1/resource/Assets0Images00011.jpg?skoid=58690ece-ec83-4ce2-9ce8-883d4d6a54ee&sktid=975f013f-7f24-47e8-a7d3-abc4752bf346&skt=2024-01-04T12%3A28%3A59Z&ske=2024-01-05T12%3A43%3A59Z&sks=b&skv=2022-11-02&sv=2022-11-02&spr=https&se=2024-01-05T12%3A43%3A59Z&sr=b&sp=r&sig=vai5tQ9tkKtKt8ChMUIXYdzWd%2BeXTJeojhj1F03DZR4%3D",
    "Jodhpur": "https://docserverpwaprodcin.blob.core.windows.net/285a469e-3ec3-4693-bc7e-310e07275a85-1/resource/Assets0Images00012.jpg?skoid=58690ece-ec83-4ce2-9ce8-883d4d6a54ee&sktid=975f013f-7f24-47e8-a7d3-abc4752bf346&skt=2024-01-04T12%3A28%3A59Z&ske=2024-01-05T12%3A43%3A59Z&sks=b&skv=2022-11-02&sv=2022-11-02&spr=https&se=2024-01-05T12%3A43%3A59Z&sr=b&sp=r&sig=Wgy9uZZnQocM7KZPRTHHYSSf0jg9go4kj7xJLfDPWMc%3D",
    "Kota": "https://docserverpwaprodcin.blob.core.windows.net/285a469e-3ec3-4693-bc7e-310e07275a85-1/resource/Assets0Images00013.jpg?skoid=58690ece-ec83-4ce2-9ce8-883d4d6a54ee&sktid=975f013f-7f24-47e8-a7d3-abc4752bf346&skt=2024-01-04T12%3A28%3A59Z&ske=2024-01-05T12%3A43%3A59Z&sks=b&skv=2022-11-02&sv=2022-11-02&spr=https&se=2024-01-05T12%3A43%3A59Z&sr=b&sp=r&sig=%2B8Kyz1B0z6cMmaM35UrMilh7b29JsAw7ff4uzHQSmR8%3D",
    "miningBottomImage": "https://docserverpwaprodcin.blob.core.windows.net/285a469e-3ec3-4693-bc7e-310e07275a85-1/resource/Assets0Images00014.jpg?skoid=58690ece-ec83-4ce2-9ce8-883d4d6a54ee&sktid=975f013f-7f24-47e8-a7d3-abc4752bf346&skt=2024-01-04T12%3A28%3A59Z&ske=2024-01-05T12%3A43%3A59Z&sks=b&skv=2022-11-02&sv=2022-11-02&spr=https&se=2024-01-05T12%3A43%3A59Z&sr=b&sp=r&sig=0jlfDZwkI3dAv%2FyCsUgZlBM3zwFYZr6cktYsqH8q4ic%3D",
    "OIl Mining logo": "https://docserverpwaprodcin.blob.core.windows.net/285a469e-3ec3-4693-bc7e-310e07275a85-1/resource/Assets0Images00015.jpg?skoid=58690ece-ec83-4ce2-9ce8-883d4d6a54ee&sktid=975f013f-7f24-47e8-a7d3-abc4752bf346&skt=2024-01-04T12%3A28%3A59Z&ske=2024-01-05T12%3A43%3A59Z&sks=b&skv=2022-11-02&sv=2022-11-02&spr=https&se=2024-01-05T12%3A43%3A59Z&sr=b&sp=r&sig=OAsUdSli4Zb3caHb%2B8fq02YIhMRgj0xp6xiQhObg3GY%3D",
    "oil_mineLOGO": "https://docserverpwaprodcin.blob.core.windows.net/285a469e-3ec3-4693-bc7e-310e07275a85-1/resource/Assets0Images00022.jpg?skoid=58690ece-ec83-4ce2-9ce8-883d4d6a54ee&sktid=975f013f-7f24-47e8-a7d3-abc4752bf346&skt=2024-01-04T12%3A28%3A59Z&ske=2024-01-05T12%3A43%3A59Z&sks=b&skv=2022-11-02&sv=2022-11-02&spr=https&se=2024-01-05T12%3A43%3A59Z&sr=b&sp=r&sig=JnTSDK2TTKukI%2F0Don7yX90rcRvhZIvZ7QRiqjLRzmM%3D",
    "oilBottomImg": "https://docserverpwaprodcin.blob.core.windows.net/285a469e-3ec3-4693-bc7e-310e07275a85-1/resource/Assets0Images00016.jpg?skoid=58690ece-ec83-4ce2-9ce8-883d4d6a54ee&sktid=975f013f-7f24-47e8-a7d3-abc4752bf346&skt=2024-01-04T12%3A28%3A59Z&ske=2024-01-05T12%3A43%3A59Z&sks=b&skv=2022-11-02&sv=2022-11-02&spr=https&se=2024-01-05T12%3A43%3A59Z&sr=b&sp=r&sig=0g9hl%2B8PSokUzEdjvX1TZm1DR1pH9yWz21L1HioUTXo%3D",
    "OilFooter": "https://docserverpwaprodcin.blob.core.windows.net/285a469e-3ec3-4693-bc7e-310e07275a85-1/resource/Assets0Images00017.jpg?skoid=58690ece-ec83-4ce2-9ce8-883d4d6a54ee&sktid=975f013f-7f24-47e8-a7d3-abc4752bf346&skt=2024-01-04T12%3A28%3A59Z&ske=2024-01-05T12%3A43%3A59Z&sks=b&skv=2022-11-02&sv=2022-11-02&spr=https&se=2024-01-05T12%3A43%3A59Z&sr=b&sp=r&sig=413o2DJqh%2BOl16mUHU3TdFqqOk1eh0gupPnpBE0vXF8%3D",
    "oilFooter_3": "https://docserverpwaprodcin.blob.core.windows.net/285a469e-3ec3-4693-bc7e-310e07275a85-1/resource/Assets0Images00019.jpg?skoid=58690ece-ec83-4ce2-9ce8-883d4d6a54ee&sktid=975f013f-7f24-47e8-a7d3-abc4752bf346&skt=2024-01-04T12%3A28%3A59Z&ske=2024-01-05T12%3A43%3A59Z&sks=b&skv=2022-11-02&sv=2022-11-02&spr=https&se=2024-01-05T12%3A43%3A59Z&sr=b&sp=r&sig=QnyuuyblMcjm%2FIIy9q9zYm7eLQHjomhKN%2FpYOnLJ5Pw%3D",
    "oilFooter_4": "https://docserverpwaprodcin.blob.core.windows.net/285a469e-3ec3-4693-bc7e-310e07275a85-1/resource/Assets0Images00020.jpg?skoid=58690ece-ec83-4ce2-9ce8-883d4d6a54ee&sktid=975f013f-7f24-47e8-a7d3-abc4752bf346&skt=2024-01-04T12%3A28%3A59Z&ske=2024-01-05T12%3A43%3A59Z&sks=b&skv=2022-11-02&sv=2022-11-02&spr=https&se=2024-01-05T12%3A43%3A59Z&sr=b&sp=r&sig=Q2CSMJZff2ZPM3ltyl1Vd1llZSLWQkm2GmqlA8s967c%3D",
    "oilFooterImage2": "https://docserverpwaprodcin.blob.core.windows.net/285a469e-3ec3-4693-bc7e-310e07275a85-1/resource/Assets0Images00018.jpg?skoid=58690ece-ec83-4ce2-9ce8-883d4d6a54ee&sktid=975f013f-7f24-47e8-a7d3-abc4752bf346&skt=2024-01-04T12%3A28%3A59Z&ske=2024-01-05T12%3A43%3A59Z&sks=b&skv=2022-11-02&sv=2022-11-02&spr=https&se=2024-01-05T12%3A43%3A59Z&sr=b&sp=r&sig=e9uLC%2FadWgxjzzdJK5Cb8rMMl7KA5GtC6%2FPfFytPlOo%3D",
    "oilMiningImageRoleBased": "https://docserverpwaprodcin.blob.core.windows.net/285a469e-3ec3-4693-bc7e-310e07275a85-1/resource/Assets0Images00021.jpg?skoid=58690ece-ec83-4ce2-9ce8-883d4d6a54ee&sktid=975f013f-7f24-47e8-a7d3-abc4752bf346&skt=2024-01-04T12%3A28%3A59Z&ske=2024-01-05T12%3A43%3A59Z&sks=b&skv=2022-11-02&sv=2022-11-02&spr=https&se=2024-01-05T12%3A43%3A59Z&sr=b&sp=r&sig=7GRQgODCWIQvnfekcY1CvUTylfrqGy5oUTY8tHk0yf4%3D",
    "pexels-codioful-(formerly-gradienta)-7130555": "https://docserverpwaprodcin.blob.core.windows.net/285a469e-3ec3-4693-bc7e-310e07275a85-1/resource/Assets0Images00023.jpg?skoid=58690ece-ec83-4ce2-9ce8-883d4d6a54ee&sktid=975f013f-7f24-47e8-a7d3-abc4752bf346&skt=2024-01-04T12%3A28%3A59Z&ske=2024-01-05T12%3A43%3A59Z&sks=b&skv=2022-11-02&sv=2022-11-02&spr=https&se=2024-01-05T12%3A43%3A59Z&sr=b&sp=r&sig=VlkdGweyubotKevP9fOer8JUoXCuTcO1e3%2B5KDwtuJk%3D",
    "pexels-gradienta-7130560": "https://docserverpwaprodcin.blob.core.windows.net/285a469e-3ec3-4693-bc7e-310e07275a85-1/resource/Assets0Images00024.jpg?skoid=58690ece-ec83-4ce2-9ce8-883d4d6a54ee&sktid=975f013f-7f24-47e8-a7d3-abc4752bf346&skt=2024-01-04T12%3A28%3A59Z&ske=2024-01-05T12%3A43%3A59Z&sks=b&skv=2022-11-02&sv=2022-11-02&spr=https&se=2024-01-05T12%3A43%3A59Z&sr=b&sp=r&sig=r8l6k1GNGs5JXQe0XQd8XIqoF%2FEQOhlxQLEE0lk4dd4%3D",
    "supervisorImage": "https://docserverpwaprodcin.blob.core.windows.net/285a469e-3ec3-4693-bc7e-310e07275a85-1/resource/Assets0Images00025.png?skoid=58690ece-ec83-4ce2-9ce8-883d4d6a54ee&sktid=975f013f-7f24-47e8-a7d3-abc4752bf346&skt=2024-01-04T12%3A28%3A59Z&ske=2024-01-05T12%3A43%3A59Z&sks=b&skv=2022-11-02&sv=2022-11-02&spr=https&se=2024-01-05T12%3A43%3A59Z&sr=b&sp=r&sig=UBTdV%2Fap9iMEcXQ30wt2aKAPvfMWUPaqWZJOXn8Wbhk%3D",
    "t85j6-alj36": "https://docserverpwaprodcin.blob.core.windows.net/285a469e-3ec3-4693-bc7e-310e07275a85-1/resource/Assets0Images00026.svg?skoid=58690ece-ec83-4ce2-9ce8-883d4d6a54ee&sktid=975f013f-7f24-47e8-a7d3-abc4752bf346&skt=2024-01-04T12%3A28%3A59Z&ske=2024-01-05T12%3A43%3A59Z&sks=b&skv=2022-11-02&sv=2022-11-02&spr=https&se=2024-01-05T12%3A43%3A59Z&sr=b&sp=r&sig=w9F0h8eCV%2Bm6eHzT7kg0wJoPJBEOgkmrhgoyat1iGxs%3D",
    "Udaipur": "https://docserverpwaprodcin.blob.core.windows.net/285a469e-3ec3-4693-bc7e-310e07275a85-1/resource/Assets0Images00027.jpg?skoid=58690ece-ec83-4ce2-9ce8-883d4d6a54ee&sktid=975f013f-7f24-47e8-a7d3-abc4752bf346&skt=2024-01-04T12%3A28%3A59Z&ske=2024-01-05T12%3A43%3A59Z&sks=b&skv=2022-11-02&sv=2022-11-02&spr=https&se=2024-01-05T12%3A43%3A59Z&sr=b&sp=r&sig=35XXxKXH5QZLyi9GjpBqquGg%2BK1QXWgIjGTyrtieSyo%3D"
  },
  "OrderComponentMetadata": {
    "8d8acd61e3154144836005b40fe0806e": 0
  },
  "OrderComponentTemplate": {
    "8d8acd61e3154144836005b40fe0806e": 0
  },
  "OrderDataSource": {
    "ComboBoxSample": 0,
    "CustomGallerySample": 1,
    "OM__RAAG_Oil_RDG_Condensate_Dispatch": 9,
    "OM_Crude_oil_sales_pipeline_inventory": 2,
    "OM_Jaipur_Terminal": 3,
    "OM_MPT_Crude_Oil": 4,
    "OM_Nos_of_Cargo_Loaded_from_Jaipur_Terminal": 5,
    "OM_Sales_to_Jaipur_Terminal": 6,
    "OM_Sales_to_Jaisalmer": 7,
    "OM_User_Iist": 8,
    "Tabs": 10,
    "temp_Tabs": 11,
    "userData1": 12
  },
  "OrderGroupControls": {},
  "OrderPcfTemplate": {},
  "OrderTemplate": {},
  "OrderXMLTemplate": {
    "button": 4,
    "circle": 8,
    "combobox": 9,
    "form": 6,
    "gallery": 3,
    "groupContainer": 0,
    "image": 1,
    "label": 2,
    "rectangle": 5,
    "text": 7
  },
  "OverridablePropertiesEntry": {
    "App": {},
    "BS_W_DataCard1": {},
    "BS_W_DataCard2": {},
    "BS_W_DataCard3": {},
    "BS_W_DataCard4": {},
    "btn_contine": {},
    "btn_contine_1": {},
    "btn_Explore": {},
    "btn_galTabSelecteds": {},
    "btn_mob_exploreNow": {},
    "btn_Trans": {},
    "btn_Trans_1": {},
    "Button1": {},
    "Button2": {},
    "Button2_1": {},
    "Button3": {},
    "Circle3": {},
    "Closing_Tank_Stock_BBLS_DataCard1": {},
    "ComboBox1": {},
    "con_kpi2": {},
    "con_kpi3": {},
    "con_kpi4": {},
    "con_kpi5": {},
    "con_main1": {},
    "con_mainHeader": {},
    "con_mainNev": {},
    "con_nevigation": {},
    "con_notification": {},
    "con_userImage": {},
    "cont_buttonHolder": {},
    "cont_ContentFormScreen": {},
    "cont_FlyingSVGArrow": {},
    "cont_FooterContent": {},
    "cont_FooterContent_1": {},
    "cont_FooterContent_2": {},
    "cont_FooterContent_3": {},
    "cont_FooterContent_4": {},
    "cont_FooterContent_5": {},
    "cont_FooterContent_6": {},
    "cont_FooterContent_7": {},
    "cont_FooterContent_8": {},
    "cont_HeaderRegionalForm_1": {},
    "cont_HeaderRegionalForm_2": {},
    "cont_kpi1": {},
    "cont_leftContent": {},
    "cont_leftSideOfMain": {},
    "cont_logIn": {},
    "cont_logIn_1": {},
    "cont_logoHeader": {},
    "cont_Main_persona": {},
    "cont_Main_persona_1": {},
    "cont_mainBackground": {},
    "cont_MainFormScreen": {},
    "cont_mainKpi": {},
    "cont_messageContent": {},
    "cont_mob_backgroundImage": {},
    "cont_mob_footerAboveContent": {},
    "cont_mob_footerAboveContent_1": {},
    "cont_mob_FooterContents": {},
    "cont_mob_LeftSideContent": {},
    "cont_mob_logoImage": {},
    "cont_mob_main(MainLanding)": {},
    "cont_personaSize": {},
    "cont_personaSize_1": {},
    "cont_rightContent": {},
    "cont_rightSideOfMain": {},
    "cont_Sales_Jaipur": {},
    "cont_Sales_Jaisalmer": {},
    "cont_Sales_Jodhpur": {},
    "cont_Sales_Kota": {},
    "cont_Sales_Udaipur": {},
    "cont_subMainPersona": {},
    "cont_subMainPersona_1": {},
    "cont_subPersona": {},
    "cont_WelcomeMessage": {},
    "Container10": {},
    "Container11": {},
    "Container13": {},
    "Container15": {},
    "Container6": {},
    "Container7": {},
    "Container8": {},
    "Container9": {},
    "Cumulative_Till_Date_DataCard1": {},
    "DataCardKey1": {},
    "DataCardKey10": {},
    "DataCardKey11": {},
    "DataCardKey12": {},
    "DataCardKey13": {},
    "DataCardKey14": {},
    "DataCardKey15": {},
    "DataCardKey16": {},
    "DataCardKey17": {},
    "DataCardKey18": {},
    "DataCardKey19": {},
    "DataCardKey2": {},
    "DataCardKey20": {},
    "DataCardKey21": {},
    "DataCardKey22": {},
    "DataCardKey23": {},
    "DataCardKey24": {},
    "DataCardKey25": {},
    "DataCardKey26": {},
    "DataCardKey27": {},
    "DataCardKey28": {},
    "DataCardKey29": {},
    "DataCardKey3": {},
    "DataCardKey30": {},
    "DataCardKey31": {},
    "DataCardKey32": {},
    "DataCardKey33": {},
    "DataCardKey34": {},
    "DataCardKey35": {},
    "DataCardKey36": {},
    "DataCardKey37": {},
    "DataCardKey4": {},
    "DataCardKey5": {},
    "DataCardKey6": {},
    "DataCardKey7": {},
    "DataCardKey8": {},
    "DataCardKey9": {},
    "DataCardValue1": {},
    "DataCardValue10": {},
    "DataCardValue11": {},
    "DataCardValue12": {},
    "DataCardValue13": {},
    "DataCardValue14": {},
    "DataCardValue15": {},
    "DataCardValue16": {},
    "DataCardValue17": {},
    "DataCardValue18": {},
    "DataCardValue19": {},
    "DataCardValue2": {},
    "DataCardValue20": {},
    "DataCardValue21": {},
    "DataCardValue22": {},
    "DataCardValue23": {},
    "DataCardValue24": {},
    "DataCardValue25": {},
    "DataCardValue26": {},
    "DataCardValue27": {},
    "DataCardValue28": {},
    "DataCardValue29": {},
    "DataCardValue3": {},
    "DataCardValue30": {},
    "DataCardValue31": {},
    "DataCardValue32": {},
    "DataCardValue33": {},
    "DataCardValue34": {},
    "DataCardValue35": {},
    "DataCardValue36": {},
    "DataCardValue37": {},
    "DataCardValue4": {},
    "DataCardValue5": {},
    "DataCardValue6": {},
    "DataCardValue7": {},
    "DataCardValue8": {},
    "DataCardValue9": {},
    "Density_15C_DataCard1": {},
    "Density_15C_DataCard2": {},
    "Duration_hours_DataCard1": {},
    "Duration_hours_DataCard2": {},
    "ErrorMessage1": {},
    "ErrorMessage10": {},
    "ErrorMessage11": {},
    "ErrorMessage12": {},
    "ErrorMessage13": {},
    "ErrorMessage14": {},
    "ErrorMessage15": {},
    "ErrorMessage16": {},
    "ErrorMessage17": {},
    "ErrorMessage18": {},
    "ErrorMessage19": {},
    "ErrorMessage2": {},
    "ErrorMessage20": {},
    "ErrorMessage21": {},
    "ErrorMessage22": {},
    "ErrorMessage23": {},
    "ErrorMessage24": {},
    "ErrorMessage25": {},
    "ErrorMessage26": {},
    "ErrorMessage27": {},
    "ErrorMessage28": {},
    "ErrorMessage29": {},
    "ErrorMessage3": {},
    "ErrorMessage30": {},
    "ErrorMessage31": {},
    "ErrorMessage32": {},
    "ErrorMessage33": {},
    "ErrorMessage34": {},
    "ErrorMessage35": {},
    "ErrorMessage36": {},
    "ErrorMessage37": {},
    "ErrorMessage4": {},
    "ErrorMessage5": {},
    "ErrorMessage6": {},
    "ErrorMessage7": {},
    "ErrorMessage8": {},
    "ErrorMessage9": {},
    "Form Screen": {},
    "Form_Sales_Jaisalmer": {},
    "Form_Screen": {},
    "Form1": {},
    "Form2": {},
    "Form3": {},
    "Form4": {},
    "Form5": {},
    "Form7": {},
    "gal_mainNev": {},
    "gal_personaSize": {},
    "gal_personaSize_1": {},
    "gal_tempTabItems": {},
    "Gallery1": {},
    "Gallery1_1": {},
    "galleryTemplate1": {},
    "galleryTemplate1_1": {},
    "galleryTemplate2": {},
    "galleryTemplate4": {},
    "galleryTemplate6": {},
    "galleryTemplate6_1": {},
    "Gross_Sales_DataCard1": {},
    "Gross_Sales_DataCard2": {},
    "Gross_Volume_pumped_DataCard1": {},
    "Gross_Volume_pumped_DataCard2": {},
    "Home Page Screen": {},
    "Host": {},
    "Image1": {},
    "Image3_1": {},
    "Image4": {},
    "Image5": {},
    "img_collaboration": {},
    "img_collaboration_1": {},
    "img_FlyingArrow": {},
    "img_logoOIlMine": {},
    "img_mob_flyingArrow": {},
    "img_mob_oilMineBackground": {},
    "img_notification": {},
    "img_oilLogoHeader_1": {},
    "img_oilLogoHeader_2": {},
    "img_OIlLogoImg": {},
    "img_oilMineImageRightSideMain": {},
    "img_persona": {},
    "img_RegionalForm_UserImage_1": {},
    "img_RegionalForm_UserImage_2": {},
    "img_relatability": {},
    "img_relatability_1": {},
    "img_safety_1": {},
    "img_safety_2": {},
    "img_solutionFooter": {},
    "img_solutionFooter_1": {},
    "img_userImage": {},
    "Label3": {},
    "Label5": {},
    "lbl_collabContent": {},
    "lbl_collabContent_1": {},
    "lbl_Collaboration": {},
    "lbl_Collaboration_1": {},
    "lbl_flex": {},
    "lbl_footSolution": {},
    "lbl_footSolution_1": {},
    "lbl_gap_1": {},
    "lbl_gap_2": {},
    "lbl_gap_3": {},
    "lbl_gap1": {},
    "lbl_LoggedInUserName_1": {},
    "lbl_LoggedInUserName_2": {},
    "lbl_LogIn": {},
    "lbl_LogIn_1": {},
    "lbl_LogoMessageOilMine": {},
    "lbl_messageContent": {},
    "lbl_MessageHeading": {},
    "lbl_mob_gap_1": {},
    "lbl_mob_Heading": {},
    "lbl_mob_headingContent": {},
    "lbl_mob_logoMessage": {},
    "lbl_mob_topGap_1": {},
    "lbl_RegionalForm_LogoHeader_1": {},
    "lbl_RegionalForm_LogoHeader_2": {},
    "lbl_relatability": {},
    "lbl_relatability_1": {},
    "lbl_relatibilityContent": {},
    "lbl_relatibilityContent_1": {},
    "lbl_safety_1": {},
    "lbl_safety_2": {},
    "lbl_safetyContent_1": {},
    "lbl_safetyContent_2": {},
    "lbl_sideGap_1": {},
    "lbl_sideGap_2": {},
    "lbl_sideGap_3": {},
    "lbl_sideGap_content": {},
    "Lbl_Size": {},
    "Lbl_Size_1": {},
    "lbl_solutionContent": {},
    "lbl_solutionContent_1": {},
    "lbl_TabItemstemp": {},
    "lbl_topfooterGap": {},
    "lbl_topfooterGap_1": {},
    "lbl_topfooterGap_10": {},
    "lbl_topfooterGap_11": {},
    "lbl_topfooterGap_12": {},
    "lbl_topfooterGap_13": {},
    "lbl_topfooterGap_14": {},
    "lbl_topfooterGap_15": {},
    "lbl_topfooterGap_2": {},
    "lbl_topfooterGap_3": {},
    "lbl_topfooterGap_4": {},
    "lbl_topfooterGap_5": {},
    "lbl_topfooterGap_6": {},
    "lbl_topfooterGap_7": {},
    "lbl_topfooterGap_8": {},
    "lbl_topfooterGap_9": {},
    "lbl_typeOfPersona": {},
    "lbl_welcome": {},
    "Main Container": {},
    "Main Landing Screen (Dynamic)": {},
    "Net_Sales_DataCard1": {},
    "Net_Sales_DataCard2": {},
    "NevigationBar": {},
    "NevigationBar_1": {},
    "Nomination_Met_DataCard1": {},
    "RAAG_Oil_RDG_DataCard1": {},
    "RAAG_Oil_RDG_DataCard2": {},
    "Receipt_Tankage_only_BBLS_DataCard1": {},
    "rect_tabItemGal": {},
    "Sales_Value_DataCard1": {},
    "Screen1": {},
    "Screen2": {},
    "ScreenContainer1": {},
    "ScreenContainer2": {},
    "Shortfall_Excess_NetMonth_DataCard1": {},
    "Shortfall_Excess_NetMonth_DataCard2": {},
    "StarVisible1": {},
    "StarVisible10": {},
    "StarVisible11": {},
    "StarVisible12": {},
    "StarVisible13": {},
    "StarVisible14": {},
    "StarVisible15": {},
    "StarVisible16": {},
    "StarVisible17": {},
    "StarVisible18": {},
    "StarVisible19": {},
    "StarVisible2": {},
    "StarVisible20": {},
    "StarVisible21": {},
    "StarVisible22": {},
    "StarVisible23": {},
    "StarVisible24": {},
    "StarVisible25": {},
    "StarVisible26": {},
    "StarVisible27": {},
    "StarVisible28": {},
    "StarVisible29": {},
    "StarVisible3": {},
    "StarVisible30": {},
    "StarVisible31": {},
    "StarVisible32": {},
    "StarVisible33": {},
    "StarVisible34": {},
    "StarVisible35": {},
    "StarVisible36": {},
    "StarVisible37": {},
    "StarVisible4": {},
    "StarVisible5": {},
    "StarVisible6": {},
    "StarVisible7": {},
    "StarVisible8": {},
    "StarVisible9": {},
    "Subtitle1_1": {},
    "Tank _DataCard1": {},
    "Tank _DataCard2": {},
    "Title_DataCard1": {},
    "Title_DataCard2": {},
    "Title_DataCard3": {},
    "Title_DataCard4": {},
    "Title_DataCard5": {},
    "Title_DataCard6": {},
    "Title_DataCard7": {},
    "Title1_1": {},
    "Title4": {},
    "Total_Gross_Pumped_DataCard1": {},
    "Total_Gross_Pumped_DataCard2": {},
    "Total_Nomination_DataCard1": {},
    "Total_Nomination_DataCard2": {},
    "Water_Drain_Quantity_BBLS_DataCard1": {}
  },
  "PCFDynamicSchemaForIRRetrievalEntry": {},
  "PCFTemplateEntry": {},
  "PublishOrderIndices": {
    "App": 0,
    "BS_W_DataCard1": 161,
    "BS_W_DataCard2": 275,
    "BS_W_DataCard3": 229,
    "BS_W_DataCard4": 341,
    "btn_contine": 318,
    "btn_contine_1": 102,
    "btn_Explore": 16,
    "btn_galTabSelecteds": 366,
    "btn_mob_exploreNow": 58,
    "btn_Trans": 317,
    "btn_Trans_1": 100,
    "Button1": 257,
    "Button2": 290,
    "Button2_1": 303,
    "Button3": 299,
    "Circle3": 374,
    "Closing_Tank_Stock_BBLS_DataCard1": 245,
    "ComboBox1": 101,
    "con_kpi2": 113,
    "con_kpi3": 114,
    "con_kpi4": 115,
    "con_kpi5": 116,
    "con_main1": 103,
    "con_mainHeader": 104,
    "con_mainNev": 370,
    "con_nevigation": 117,
    "con_notification": 107,
    "con_userImage": 109,
    "cont_buttonHolder": 14,
    "cont_ContentFormScreen": 362,
    "cont_FlyingSVGArrow": 17,
    "cont_FooterContent": 20,
    "cont_FooterContent_1": 21,
    "cont_FooterContent_2": 27,
    "cont_FooterContent_3": 33,
    "cont_FooterContent_4": 39,
    "cont_FooterContent_5": 62,
    "cont_FooterContent_6": 68,
    "cont_FooterContent_7": 75,
    "cont_FooterContent_8": 81,
    "cont_HeaderRegionalForm_1": 119,
    "cont_HeaderRegionalForm_2": 357,
    "cont_kpi1": 112,
    "cont_leftContent": 363,
    "cont_leftSideOfMain": 1,
    "cont_logIn": 311,
    "cont_logIn_1": 90,
    "cont_logoHeader": 2,
    "cont_Main_persona": 309,
    "cont_Main_persona_1": 87,
    "cont_mainBackground": 0,
    "cont_MainFormScreen": 356,
    "cont_mainKpi": 111,
    "cont_messageContent": 9,
    "cont_mob_backgroundImage": 51,
    "cont_mob_footerAboveContent": 61,
    "cont_mob_footerAboveContent_1": 74,
    "cont_mob_FooterContents": 60,
    "cont_mob_LeftSideContent": 53,
    "cont_mob_logoImage": 48,
    "cont_mob_main(MainLanding)": 47,
    "cont_personaSize": 316,
    "cont_personaSize_1": 95,
    "cont_rightContent": 369,
    "cont_rightSideOfMain": 45,
    "cont_Sales_Jaipur": 320,
    "cont_Sales_Jaisalmer": 324,
    "cont_Sales_Jodhpur": 321,
    "cont_Sales_Kota": 322,
    "cont_Sales_Udaipur": 323,
    "cont_subMainPersona": 310,
    "cont_subMainPersona_1": 89,
    "cont_subPersona": 96,
    "cont_WelcomeMessage": 5,
    "Container10": 373,
    "Container11": 295,
    "Container13": 300,
    "Container15": 298,
    "Container6": 292,
    "Container7": 293,
    "Container8": 307,
    "Container9": 294,
    "Cumulative_Till_Date_DataCard1": 172,
    "DataCardKey1": 128,
    "DataCardKey10": 267,
    "DataCardKey11": 272,
    "DataCardKey12": 277,
    "DataCardKey13": 282,
    "DataCardKey14": 287,
    "DataCardKey15": 169,
    "DataCardKey16": 174,
    "DataCardKey17": 329,
    "DataCardKey18": 180,
    "DataCardKey19": 185,
    "DataCardKey2": 133,
    "DataCardKey20": 190,
    "DataCardKey21": 334,
    "DataCardKey22": 196,
    "DataCardKey23": 201,
    "DataCardKey24": 206,
    "DataCardKey25": 211,
    "DataCardKey26": 216,
    "DataCardKey27": 221,
    "DataCardKey28": 226,
    "DataCardKey29": 231,
    "DataCardKey3": 138,
    "DataCardKey30": 339,
    "DataCardKey31": 237,
    "DataCardKey32": 242,
    "DataCardKey33": 247,
    "DataCardKey34": 252,
    "DataCardKey35": 344,
    "DataCardKey36": 349,
    "DataCardKey37": 354,
    "DataCardKey4": 143,
    "DataCardKey5": 148,
    "DataCardKey6": 153,
    "DataCardKey7": 158,
    "DataCardKey8": 163,
    "DataCardKey9": 262,
    "DataCardValue1": 129,
    "DataCardValue10": 268,
    "DataCardValue11": 273,
    "DataCardValue12": 278,
    "DataCardValue13": 283,
    "DataCardValue14": 288,
    "DataCardValue15": 170,
    "DataCardValue16": 175,
    "DataCardValue17": 327,
    "DataCardValue18": 181,
    "DataCardValue19": 186,
    "DataCardValue2": 134,
    "DataCardValue20": 191,
    "DataCardValue21": 332,
    "DataCardValue22": 197,
    "DataCardValue23": 202,
    "DataCardValue24": 207,
    "DataCardValue25": 212,
    "DataCardValue26": 217,
    "DataCardValue27": 222,
    "DataCardValue28": 227,
    "DataCardValue29": 232,
    "DataCardValue3": 139,
    "DataCardValue30": 337,
    "DataCardValue31": 238,
    "DataCardValue32": 243,
    "DataCardValue33": 248,
    "DataCardValue34": 253,
    "DataCardValue35": 342,
    "DataCardValue36": 347,
    "DataCardValue37": 352,
    "DataCardValue4": 144,
    "DataCardValue5": 149,
    "DataCardValue6": 154,
    "DataCardValue7": 159,
    "DataCardValue8": 164,
    "DataCardValue9": 263,
    "Density_15C_DataCard1": 285,
    "Density_15C_DataCard2": 351,
    "Duration_hours_DataCard1": 156,
    "Duration_hours_DataCard2": 224,
    "ErrorMessage1": 130,
    "ErrorMessage10": 269,
    "ErrorMessage11": 274,
    "ErrorMessage12": 279,
    "ErrorMessage13": 284,
    "ErrorMessage14": 289,
    "ErrorMessage15": 171,
    "ErrorMessage16": 176,
    "ErrorMessage17": 330,
    "ErrorMessage18": 182,
    "ErrorMessage19": 187,
    "ErrorMessage2": 135,
    "ErrorMessage20": 192,
    "ErrorMessage21": 335,
    "ErrorMessage22": 198,
    "ErrorMessage23": 203,
    "ErrorMessage24": 208,
    "ErrorMessage25": 213,
    "ErrorMessage26": 218,
    "ErrorMessage27": 223,
    "ErrorMessage28": 228,
    "ErrorMessage29": 233,
    "ErrorMessage3": 140,
    "ErrorMessage30": 340,
    "ErrorMessage31": 239,
    "ErrorMessage32": 244,
    "ErrorMessage33": 249,
    "ErrorMessage34": 254,
    "ErrorMessage35": 345,
    "ErrorMessage36": 350,
    "ErrorMessage37": 355,
    "ErrorMessage4": 145,
    "ErrorMessage5": 150,
    "ErrorMessage6": 155,
    "ErrorMessage7": 160,
    "ErrorMessage8": 165,
    "ErrorMessage9": 264,
    "Form Screen": 10,
    "Form_Sales_Jaisalmer": 325,
    "Form_Screen": 25,
    "Form1": 125,
    "Form2": 259,
    "Form3": 166,
    "Form4": 177,
    "Form5": 193,
    "Form7": 234,
    "gal_mainNev": 371,
    "gal_personaSize": 314,
    "gal_personaSize_1": 93,
    "gal_tempTabItems": 364,
    "Gallery1": 255,
    "Gallery1_1": 301,
    "galleryTemplate1": 256,
    "galleryTemplate1_1": 302,
    "galleryTemplate2": 365,
    "galleryTemplate4": 372,
    "galleryTemplate6": 315,
    "galleryTemplate6_1": 94,
    "Gross_Sales_DataCard1": 265,
    "Gross_Sales_DataCard2": 331,
    "Gross_Volume_pumped_DataCard1": 131,
    "Gross_Volume_pumped_DataCard2": 199,
    "Home Page Screen": 63,
    "Host": 0,
    "Image1": 88,
    "Image3_1": 304,
    "Image4": 308,
    "Image5": 375,
    "img_collaboration": 23,
    "img_collaboration_1": 64,
    "img_FlyingArrow": 19,
    "img_logoOIlMine": 49,
    "img_mob_flyingArrow": 59,
    "img_mob_oilMineBackground": 52,
    "img_notification": 108,
    "img_oilLogoHeader_1": 120,
    "img_oilLogoHeader_2": 358,
    "img_OIlLogoImg": 3,
    "img_oilMineImageRightSideMain": 46,
    "img_persona": 98,
    "img_RegionalForm_UserImage_1": 122,
    "img_RegionalForm_UserImage_2": 361,
    "img_relatability": 35,
    "img_relatability_1": 77,
    "img_safety_1": 29,
    "img_safety_2": 70,
    "img_solutionFooter": 41,
    "img_solutionFooter_1": 83,
    "img_userImage": 110,
    "Label3": 296,
    "Label5": 297,
    "lbl_collabContent": 26,
    "lbl_collabContent_1": 67,
    "lbl_Collaboration": 25,
    "lbl_Collaboration_1": 66,
    "lbl_flex": 106,
    "lbl_footSolution": 43,
    "lbl_footSolution_1": 85,
    "lbl_gap_1": 6,
    "lbl_gap_2": 8,
    "lbl_gap_3": 13,
    "lbl_gap1": 97,
    "lbl_LoggedInUserName_1": 121,
    "lbl_LoggedInUserName_2": 360,
    "lbl_LogIn": 312,
    "lbl_LogIn_1": 91,
    "lbl_LogoMessageOilMine": 4,
    "lbl_messageContent": 11,
    "lbl_MessageHeading": 7,
    "lbl_mob_gap_1": 57,
    "lbl_mob_Heading": 55,
    "lbl_mob_headingContent": 56,
    "lbl_mob_logoMessage": 50,
    "lbl_mob_topGap_1": 54,
    "lbl_RegionalForm_LogoHeader_1": 123,
    "lbl_RegionalForm_LogoHeader_2": 359,
    "lbl_relatability": 37,
    "lbl_relatability_1": 79,
    "lbl_relatibilityContent": 38,
    "lbl_relatibilityContent_1": 80,
    "lbl_safety_1": 31,
    "lbl_safety_2": 72,
    "lbl_safetyContent_1": 32,
    "lbl_safetyContent_2": 73,
    "lbl_sideGap_1": 10,
    "lbl_sideGap_2": 15,
    "lbl_sideGap_3": 18,
    "lbl_sideGap_content": 12,
    "Lbl_Size": 313,
    "Lbl_Size_1": 92,
    "lbl_solutionContent": 44,
    "lbl_solutionContent_1": 86,
    "lbl_TabItemstemp": 367,
    "lbl_topfooterGap": 22,
    "lbl_topfooterGap_1": 24,
    "lbl_topfooterGap_10": 69,
    "lbl_topfooterGap_11": 71,
    "lbl_topfooterGap_12": 76,
    "lbl_topfooterGap_13": 78,
    "lbl_topfooterGap_14": 82,
    "lbl_topfooterGap_15": 84,
    "lbl_topfooterGap_2": 28,
    "lbl_topfooterGap_3": 30,
    "lbl_topfooterGap_4": 34,
    "lbl_topfooterGap_5": 36,
    "lbl_topfooterGap_6": 40,
    "lbl_topfooterGap_7": 42,
    "lbl_topfooterGap_8": 63,
    "lbl_topfooterGap_9": 65,
    "lbl_typeOfPersona": 99,
    "lbl_welcome": 105,
    "Main Container": 319,
    "Main Landing Screen (Dynamic)": 79,
    "Net_Sales_DataCard1": 270,
    "Net_Sales_DataCard2": 336,
    "NevigationBar": 1,
    "NevigationBar_1": 118,
    "Nomination_Met_DataCard1": 188,
    "RAAG_Oil_RDG_DataCard1": 146,
    "RAAG_Oil_RDG_DataCard2": 214,
    "Receipt_Tankage_only_BBLS_DataCard1": 240,
    "rect_tabItemGal": 368,
    "Sales_Value_DataCard1": 183,
    "Screen1": 183,
    "Screen2": 356,
    "ScreenContainer1": 291,
    "ScreenContainer2": 124,
    "Shortfall_Excess_NetMonth_DataCard1": 280,
    "Shortfall_Excess_NetMonth_DataCard2": 346,
    "StarVisible1": 127,
    "StarVisible10": 266,
    "StarVisible11": 271,
    "StarVisible12": 276,
    "StarVisible13": 281,
    "StarVisible14": 286,
    "StarVisible15": 168,
    "StarVisible16": 173,
    "StarVisible17": 328,
    "StarVisible18": 179,
    "StarVisible19": 184,
    "StarVisible2": 132,
    "StarVisible20": 189,
    "StarVisible21": 333,
    "StarVisible22": 195,
    "StarVisible23": 200,
    "StarVisible24": 205,
    "StarVisible25": 210,
    "StarVisible26": 215,
    "StarVisible27": 220,
    "StarVisible28": 225,
    "StarVisible29": 230,
    "StarVisible3": 137,
    "StarVisible30": 338,
    "StarVisible31": 236,
    "StarVisible32": 241,
    "StarVisible33": 246,
    "StarVisible34": 251,
    "StarVisible35": 343,
    "StarVisible36": 348,
    "StarVisible37": 353,
    "StarVisible4": 142,
    "StarVisible5": 147,
    "StarVisible6": 152,
    "StarVisible7": 157,
    "StarVisible8": 162,
    "StarVisible9": 261,
    "Subtitle1_1": 306,
    "Tank _DataCard1": 151,
    "Tank _DataCard2": 219,
    "Title_DataCard1": 126,
    "Title_DataCard2": 260,
    "Title_DataCard3": 167,
    "Title_DataCard4": 178,
    "Title_DataCard5": 194,
    "Title_DataCard6": 235,
    "Title_DataCard7": 326,
    "Title1_1": 305,
    "Title4": 258,
    "Total_Gross_Pumped_DataCard1": 141,
    "Total_Gross_Pumped_DataCard2": 209,
    "Total_Nomination_DataCard1": 136,
    "Total_Nomination_DataCard2": 204,
    "Water_Drain_Quantity_BBLS_DataCard1": 250
  },
  "ResourcesJsonIndices": {
    "Image-1649": 1,
    "Image-64f5c287aa639b5b91ad3b0f_Rectangle (2)": 2,
    "Image-7f951bda68241a57aa84929a95f120f9f082a9a0-1440x1054": 3,
    "Image-9d2ea1b508c12a7d974e238d426589ad-removebg-preview": 4,
    "Image-adminImage": 5,
    "Image-blue-gradient-background": 6,
    "Image-field-with-oil-pump-jacks-surrounded-by-greenery-sunlight": 7,
    "Image-Hawa-Mahal-Jaipur": 8,
    "Image-imageedit_1_7296434249": 10,
    "Image-image-removebg-preview": 9,
    "Image-JAISALMER": 11,
    "Image-Jodhpur": 12,
    "Image-Kota": 13,
    "Image-miningBottomImage": 14,
    "Image-OIl Mining logo": 15,
    "Image-oil_mineLOGO": 22,
    "Image-oilBottomImg": 16,
    "Image-OilFooter": 17,
    "Image-oilFooter_3": 19,
    "Image-oilFooter_4": 20,
    "Image-oilFooterImage2": 18,
    "Image-oilMiningImageRoleBased": 21,
    "Image-pexels-codioful-(formerly-gradienta)-7130555": 23,
    "Image-pexels-gradienta-7130560": 24,
    "Image-SampleImage": 0,
    "Image-supervisorImage": 25,
    "Image-t85j6-alj36": 26,
    "Image-Udaipur": 27
  },
  "RuleScreenIdWithoutScreen": {},
  "TemplateVersions": {},
  "VolatileProperties": {
    "AnalysisLoadTime": 1.9024544,
    "ControlCount": {
      "8d8acd61e3154144836005b40fe0806e": 2,
      "button": 11,
      "circle": 1,
      "combobox": 1,
      "form": 7,
      "gallery": 6,
      "galleryTemplate": 6,
      "groupContainer": 67,
      "image": 25,
      "label": 176,
      "rectangle": 1,
      "screen": 6,
      "text": 37,
      "typedDataCard": 37
    },
    "DeserializationLoadTime": 4.1413291
  },
  "WasLocalDatabaseReferencesEmpty": true
}